flintypy/__init__.py
flintypy/v_stat.py
flintypy-0.0.0.dist-info/.DS_Store
flintypy-0.0.0.dist-info/LICENSE
flintypy-0.0.0.dist-info/METADATA
flintypy-0.0.0.dist-info/WHEEL
flintypy-0.0.0.dist-info/top_level.txt
flintypy-0.0.0.dist-info/RECORD
