Metadata-Version: 2.1
Name: flintypy
Version: 0.0.0
Summary: Flexible and Interpretable Non-parametric Tests of Exchangeability
Home-page: UNKNOWN
Author: Alan Aw, Jeffrey Spence
Author-email: alanaw1@berkeley.edu, jspence@stanford.edu
License: GPLv3
Platform: UNKNOWN
License-File: LICENSE
Requires-Dist: pytest
Requires-Dist: gmpy2
Requires-Dist: numpy (>=1.16.5)
Requires-Dist: scipy (>=1.5.0)
Requires-Dist: numba (>=0.53.0)
